sphinxify.py
sphinxify-0.12.dist-info/entry_points.txt
sphinxify-0.12.dist-info/licenses/LICENSE
sphinxify-0.12.dist-info/WHEEL
sphinxify-0.12.dist-info/METADATA
sphinxify-0.12.dist-info/RECORD
