Metadata-Version: 2.4
Name: sphinxify
Version: 0.12
Summary: Convert Javadoc to Sphinx docstrings.
Keywords: javadoc,sphinx,doxygen
Author-email: David Vo <david@vovo.id.au>
Requires-Python: >=3.6
License-Expression: BSD-3-Clause
Classifier: Development Status :: 5 - Production/Stable
Classifier: Intended Audience :: Developers
Classifier: Operating System :: OS Independent
Classifier: Programming Language :: Python :: 3
Classifier: Programming Language :: Python :: 3 :: Only
Classifier: Programming Language :: Python :: 3.6
Classifier: Programming Language :: Python :: 3.7
Classifier: Programming Language :: Python :: 3.8
Classifier: Programming Language :: Python :: 3.9
Classifier: Programming Language :: Python :: 3.10
Classifier: Programming Language :: Python :: 3.11
Classifier: Programming Language :: Python :: 3.12
Classifier: Programming Language :: Python :: 3.13
License-File: LICENSE
Requires-Dist: dataclasses; python_version < '3.7'
Project-URL: Source, https://github.com/auscompgeek/sphinxify
